LICENSE
MANIFEST.in
README.md
cigar.py
ez_setup.py
setup.py
cigar.egg-info/PKG-INFO
cigar.egg-info/SOURCES.txt
cigar.egg-info/dependency_links.txt
cigar.egg-info/top_level.txt