Metadata-Version: 1.1
Name: cigar
Version: 0.1.3
Summary: manipulate SAM cigar strings
Home-page: https://github.com/brentp/cigar
Author: Brent Pedersen
Author-email: bpederse@gmail.com
License: MIT
Platform: UNKNOWN
Classifier: Topic :: Scientific/Engineering :: Bio-Informatics
Classifier: Programming Language :: Python :: 2
Classifier: Programming Language :: Python :: 3
